dewi_utils/__init__.py
dewi_utils/appconfigsetup.py
dewi_utils/archives.py
dewi_utils/config.py
dewi_utils/config_page.py
dewi_utils/csv.py
dewi_utils/files.py
dewi_utils/git.py
dewi_utils/kayako_rest.py
dewi_utils/lithurgical.py
dewi_utils/lock.py
dewi_utils/mailer.py
dewi_utils/network.py
dewi_utils/process.py
dewi_utils/render.py
dewi_utils/screen.py
dewi_utils/string.py
dewi_utils/threading.py
dewi_utils/xml.py
dewi_utils/rrdtool/__init__.py
dewi_utils/rrdtool/config.py
dewi_utils/rrdtool/interval.py
dewi_utils/rrdtool/loader.py
dewi_utils/rrdtool/modifiers.py
dewi_utils/rrdtool/rrdtool.py
dewi_utils/rrdtool/writer.py
dewi_utils-3.1.0.dist-info/COPYING
dewi_utils-3.1.0.dist-info/METADATA
dewi_utils-3.1.0.dist-info/WHEEL
dewi_utils-3.1.0.dist-info/top_level.txt
dewi_utils-3.1.0.dist-info/zip-safe
dewi_utils-3.1.0.dist-info/RECORD
